LICENSE
MANIFEST.in
README.md
setup.py
xmltramp2/__init__.py
xmltramp2/tests.py
xmltramp2/xmltramp.py
xmltramp2.egg-info/PKG-INFO
xmltramp2.egg-info/SOURCES.txt
xmltramp2.egg-info/dependency_links.txt
xmltramp2.egg-info/not-zip-safe
xmltramp2.egg-info/requires.txt
xmltramp2.egg-info/top_level.txt