Metadata-Version: 1.1
Name: xmltramp2
Version: 3.0.8
Summary: A modern refactoring of the venerable xmltramp application
Home-page: https://github.com/tBaxter/xmltramp2
Author: Tim Baxter
Author-email: mail.baxter@gmail.com
License: GPL
Platform: UNKNOWN
Classifier: Intended Audience :: Developers
Classifier: License :: OSI Approved :: GNU General Public License v2 (GPLv2)
Classifier: Operating System :: OS Independent
Classifier: Programming Language :: Python :: 2
Classifier: Programming Language :: Python :: 2.7
Classifier: Programming Language :: Python :: 3
Classifier: Programming Language :: Python :: 3.4
Classifier: Topic :: Text Processing :: Markup :: XML
